{
    "NtQuerySymbolicLinkObject": {
        "-5": {
            "NtOpenSymbolicLinkObject NtEnumerateKey NtOpenFile NtEnumerateKey NtWaitForWorkViaWorkerFactory": 1,
            "NtOpenSymbolicLinkObject NtProtectVirtualMemory NtOpenFile NtProtectVirtualMemory NtWaitForSingleObject": 1,
            "NtOpenSymbolicLinkObject NtQueryObject NtOpenDirectoryObject NtQueryInformationProcess NtAllocateVirtualMemory": 1,
            "NtOpenSymbolicLinkObject NtQueryObject NtOpenDirectoryObject NtQueryInformationProcess NtProtectVirtualMemory": 1,
            "NtProtectVirtualMemory NtOpenSymbolicLinkObject NtOpenFile NtQueryInformationToken NtWaitForSingleObject": 1
        },
        "-4": {
            "NtOpenSymbolicLinkObject NtEnumerateKey NtOpenFile NtEnumerateKey": 1,
            "NtOpenSymbolicLinkObject NtOpenDirectoryObject NtFreeVirtualMemory NtAllocateVirtualMemory": 6,
            "NtOpenSymbolicLinkObject NtProtectVirtualMemory NtOpenFile NtProtectVirtualMemory": 1,
            "NtOpenSymbolicLinkObject NtQueryObject NtOpenDirectoryObject NtFreeVirtualMemory": 6,
            "NtProtectVirtualMemory NtOpenSymbolicLinkObject NtOpenFile NtQueryInformationToken": 1
        },
        "-3": {
            "NtOpenSymbolicLinkObject NtEnumerateKey NtOpenFile": 1,
            "NtOpenSymbolicLinkObject NtOpenDirectoryObject NtFreeVirtualMemory": 6,
            "NtOpenSymbolicLinkObject NtProtectVirtualMemory NtOpenFile": 1,
            "NtOpenSymbolicLinkObject NtQueryObject NtOpenDirectoryObject": 100,
            "NtProtectVirtualMemory NtOpenSymbolicLinkObject NtOpenFile": 1
        },
        "-2": {
            "NtOpenSymbolicLinkObject NtEnumerateKey": 1,
            "NtOpenSymbolicLinkObject NtOpenDirectoryObject": 6,
            "NtOpenSymbolicLinkObject NtProtectVirtualMemory": 1,
            "NtOpenSymbolicLinkObject NtQueryObject": 100,
            "NtProtectVirtualMemory NtOpenSymbolicLinkObject": 1
        },
        "-1": {
            "NtOpenSymbolicLinkObject": 108,
            "NtProtectVirtualMemory": 1
        },
        "1": {
            "NtClose": 106,
            "NtEnumerateKey": 1,
            "NtProtectVirtualMemory": 1,
            "NtQueryObject": 1
        },
        "2": {
            "NtClose NtCreateEvent": 6,
            "NtClose NtProtectVirtualMemory": 6,
            "NtEnumerateKey NtClose": 1,
            "NtProtectVirtualMemory NtClose": 1,
            "NtQueryObject NtClose": 1
        },
        "3": {
            "NtClose NtClose NtProtectVirtualMemory": 1,
            "NtClose NtClose NtQueryInformationProcess": 2,
            "NtEnumerateKey NtClose NtEnumerateKey": 1,
            "NtProtectVirtualMemory NtClose NtQueryInformationToken": 1,
            "NtQueryObject NtClose NtQueryVolumeInformationFile": 1
        },
        "4": {
            "NtClose NtClose NtProtectVirtualMemory NtProtectVirtualMemory": 1,
            "NtClose NtClose NtQueryInformationProcess NtQueryInformationProcess": 2,
            "NtEnumerateKey NtClose NtEnumerateKey NtQueryVolumeInformationFile": 1,
            "NtProtectVirtualMemory NtClose NtQueryInformationToken NtQueryVolumeInformationFile": 1,
            "NtQueryObject NtClose NtQueryVolumeInformationFile NtQueryKey": 1
        },
        "5": {
            "NtClose NtClose NtOpenThreadToken NtOpenThreadToken NtOpenThreadToken": 1,
            "NtClose NtClose NtProtectVirtualMemory NtProtectVirtualMemory NtQueryInformationProcess": 1,
            "NtEnumerateKey NtClose NtEnumerateKey NtQueryVolumeInformationFile NtClose": 1,
            "NtProtectVirtualMemory NtClose NtQueryInformationToken NtQueryVolumeInformationFile NtClose": 1,
            "NtQueryObject NtClose NtQueryVolumeInformationFile NtQueryKey NtClose": 1
        }
    }
}