{
    "NtQuerySecurityObject": {
        "-5": {
            "NtOpenFile NtApphelpCacheControl NtClose NtQuerySecurityObject NtQuerySecurityObject": 77,
            "NtQuerySecurityObject NtOpenFile NtApphelpCacheControl NtClose NtQuerySecurityObject": 77
        },
        "-4": {
            "NtOpenFile NtApphelpCacheControl NtClose NtQuerySecurityObject": 77,
            "NtQuerySecurityObject NtOpenFile NtApphelpCacheControl NtClose": 77
        },
        "-3": {
            "NtOpenFile NtApphelpCacheControl NtClose": 77,
            "NtQuerySecurityObject NtOpenFile NtApphelpCacheControl": 83
        },
        "-2": {
            "NtOpenFile NtApphelpCacheControl": 83,
            "NtQuerySecurityObject NtOpenFile": 171
        },
        "-1": {
            "NtOpenFile": 174,
            "NtQuerySecurityObject": 173
        },
        "1": {
            "NtClose": 175,
            "NtQuerySecurityObject": 173
        },
        "2": {
            "NtClose NtApphelpCacheControl": 143,
            "NtQuerySecurityObject NtClose": 171
        },
        "3": {
            "NtClose NtApphelpCacheControl NtOpenFile": 77,
            "NtQuerySecurityObject NtClose NtApphelpCacheControl": 142
        },
        "4": {
            "NtClose NtApphelpCacheControl NtOpenFile NtQuerySecurityObject": 77,
            "NtQuerySecurityObject NtClose NtApphelpCacheControl NtOpenFile": 77
        },
        "5": {
            "NtClose NtApphelpCacheControl NtOpenFile NtQuerySecurityObject NtQuerySecurityObject": 77,
            "NtQuerySecurityObject NtClose NtApphelpCacheControl NtOpenFile NtQuerySecurityObject": 77
        }
    }
}