{
    "NtUserReleaseDC": {
        "-5": {
            "NtGdiCreateDIBitmapInternal NtUserGetDC NtGdiSelectBitmap NtGdiRestoreDC NtGdiSelectBitmap": 16,
            "NtUserGetProp NtUserGetWindowDC NtUserGetProp NtUserGetScrollBarInfo NtUserGetProp": 22
        },
        "-4": {
            "NtGdiCreateDIBitmapInternal NtUserGetDC NtGdiSelectBitmap NtGdiRestoreDC": 16,
            "NtUserGetProp NtUserGetWindowDC NtUserGetProp NtUserGetScrollBarInfo": 24
        },
        "-3": {
            "NtGdiCreateDIBitmapInternal NtUserGetDC NtGdiSelectBitmap": 20,
            "NtUserGetProp NtUserGetWindowDC NtUserGetProp": 24
        },
        "-2": {
            "NtGdiCreateDIBitmapInternal NtUserGetDC": 27,
            "NtUserGetProp NtUserGetWindowDC": 24
        },
        "-1": {
            "NtGdiCreateDIBitmapInternal": 29,
            "NtUserGetProp": 30
        },
        "1": {
            "NtGdiSelectBitmap": 48,
            "NtUserGetProp": 17
        },
        "2": {
            "NtGdiSelectBitmap NtGdiGetDCforBitmap": 34,
            "NtUserSetWindowLongPtr NtContinueEx": 16
        },
        "3": {
            "NtGdiSelectBitmap NtGdiGetDCforBitmap NtGdiSaveDC": 34,
            "NtUserSetWindowLongPtr NtContinueEx NtCallbackReturn": 16
        },
        "4": {
            "NtGdiSelectBitmap NtGdiGetDCforBitmap NtGdiSaveDC NtGdiSelectBitmap": 34,
            "NtUserSetWindowLongPtr NtContinueEx NtCallbackReturn NtUserGetProp": 15
        },
        "5": {
            "NtGdiSelectBitmap NtGdiGetDCforBitmap NtGdiSaveDC NtGdiSelectBitmap NtGdiGetDCObject": 34,
            "NtUserSetWindowLongPtr NtContinueEx NtCallbackReturn NtUserGetProp NtUserIsTopLevelWindow": 15
        }
    }
}